{"client":"Thunder Client","collectionName":"Sistema de reservas de mesas en restaurantes","dateExported":"2021-05-10T17:27:56.559Z","version":"1.1","folders":[{"containerId":"","sortNum":20000,"name":"1.Administración de datos del restaurante (CRUD: POST, PUT, DELETE, GET)","_id":"b4032801-c3fa-46c2-933b-c8ece7163f3a","created":"2021-05-10T16:34:45.900Z"}],"requests":[{"containerId":"b4032801-c3fa-46c2-933b-c8ece7163f3a","sortNum":20000,"headers":[{"name":"Accept","value":"*/*"},{"name":"User-Agent","value":"Thunder Client (https://www.thunderclient.io)"}],"colId":"c8ad78ea-1d5c-4db8-84c1-0b4d10ff0206","name":"Crear restaurante","url":"http://localhost:8080/restaurantes","method":"POST","modified":"2021-05-10T16:40:12.645Z","created":"2021-05-10T16:35:16.872Z","_id":"1f5f37db-0cd1-4e44-8ed7-99a44a7fd74b","body":{"type":"json","raw":"{\n    \"nombre\":\"San Pietro Restaurante\",\n    \"direccion\":\"Ave. Doctor Guido Boggiani - Ciclovia 5641, Asunción\"\n}"},"tests":[]},{"containerId":"b4032801-c3fa-46c2-933b-c8ece7163f3a","sortNum":30000,"headers":[{"name":"Accept","value":"*/*"},{"name":"User-Agent","value":"Thunder Client (https://www.thunderclient.io)"}],"colId":"c8ad78ea-1d5c-4db8-84c1-0b4d10ff0206","name":"Obtener restaurante by ID","url":"http://localhost:8080/restaurantes/1","method":"GET","modified":"2021-05-10T17:23:30.655Z","created":"2021-05-10T17:22:59.645Z","_id":"29982ef2-e738-4d95-9300-b29eb8e7e6a8","tests":[]},{"containerId":"b4032801-c3fa-46c2-933b-c8ece7163f3a","sortNum":40000,"headers":[{"name":"Accept","value":"*/*"},{"name":"User-Agent","value":"Thunder Client (https://www.thunderclient.io)"}],"colId":"c8ad78ea-1d5c-4db8-84c1-0b4d10ff0206","name":"Obtener todos los restaurantes","url":"http://localhost:8080/restaurantes/1","method":"GET","modified":"2021-05-10T17:24:20.713Z","created":"2021-05-10T17:23:59.419Z","_id":"68e1728e-a093-41d4-ba02-fd2e05be4361","tests":[]},{"containerId":"b4032801-c3fa-46c2-933b-c8ece7163f3a","sortNum":50000,"headers":[{"name":"Accept","value":"*/*"},{"name":"User-Agent","value":"Thunder Client (https://www.thunderclient.io)"}],"colId":"c8ad78ea-1d5c-4db8-84c1-0b4d10ff0206","name":"Actualizar restaurante by ID","url":"http://localhost:8080/restaurantes/1","method":"PUT","modified":"2021-05-10T17:26:08.513Z","created":"2021-05-10T17:25:03.318Z","_id":"18d74796-5e67-4714-bf89-53ba2f09fc39","body":{"type":"json","raw":"{\r\n    \"nombre\":\"Nuevo Nombre\",\r\n    \"direccion\":\"Nueva dirección\"\r\n}"},"tests":[]},{"containerId":"b4032801-c3fa-46c2-933b-c8ece7163f3a","sortNum":60000,"headers":[{"name":"Accept","value":"*/*"},{"name":"User-Agent","value":"Thunder Client (https://www.thunderclient.io)"}],"colId":"c8ad78ea-1d5c-4db8-84c1-0b4d10ff0206","name":"Borrar restaurante by ID","url":"http://localhost:8080/restaurantes/1","method":"DELETE","modified":"2021-05-10T17:26:55.335Z","created":"2021-05-10T17:26:44.425Z","_id":"681355c4-311c-4b5a-aaad-42ea569964f7","tests":[]},{"containerId":"b4032801-c3fa-46c2-933b-c8ece7163f3a","sortNum":70000,"headers":[{"name":"Accept","value":"*/*"},{"name":"User-Agent","value":"Thunder Client (https://www.thunderclient.io)"}],"colId":"c8ad78ea-1d5c-4db8-84c1-0b4d10ff0206","name":"Borrar todos los restaurantes ","url":"http://localhost:8080/restaurantes","method":"DELETE","modified":"2021-05-10T17:27:27.639Z","created":"2021-05-10T17:27:18.920Z","_id":"26c57069-cb47-43c0-80a9-f550f235bf8b","tests":[]}]}
